{
  "signals": [
    {
      "signalId": "2026-04-23_0_ICICIBANK",
      "date": "2026-04-23",
      "captureTime": "18:55",
      "symbol": "ICICIBANK",
      "sector": "Private Sector Bank",
      "signalType": "BUY",
      "entry": 1367.6,
      "target": 1490.76,
      "stopLoss": 1324.62,
      "rsi": 79.91,
      "techScore": 70,
      "macd": "BULLISH",
      "isSwing": false,
      "status": "PENDING",
      "exitPrice": null,
      "exitTime": null,
      "pnlPct": null,
      "resolvedBy": null,
      "highReached": 1367.6,
      "lowReached": 1367.6,
      "lastLTP": 1367.6
    },
    {
      "signalId": "2026-04-23_1_DATAPATTNS",
      "date": "2026-04-23",
      "captureTime": "18:55",
      "symbol": "DATAPATTNS",
      "sector": "Aerospace & Defense",
      "signalType": "BUY",
      "entry": 3828.3,
      "target": 4074.5,
      "stopLoss": 3266.75,
      "rsi": 84.47,
      "techScore": 70,
      "macd": "BULLISH",
      "isSwing": false,
      "status": "PENDING",
      "exitPrice": null,
      "exitTime": null,
      "pnlPct": null,
      "resolvedBy": null,
      "highReached": 3828.3,
      "lowReached": 3828.3,
      "lastLTP": 3828.3
    },
    {
      "signalId": "2026-04-23_2_OFSS",
      "date": "2026-04-23",
      "captureTime": "18:55",
      "symbol": "OFSS",
      "sector": "Software Products",
      "signalType": "STRONG BUY",
      "entry": 8126.5,
      "target": 8633.25,
      "stopLoss": 7500.38,
      "rsi": 86.71,
      "techScore": 75,
      "macd": "BULLISH",
      "isSwing": false,
      "status": "PENDING",
      "exitPrice": null,
      "exitTime": null,
      "pnlPct": null,
      "resolvedBy": null,
      "highReached": 8126.5,
      "lowReached": 8126.5,
      "lastLTP": 8126.5
    },
    {
      "signalId": "2026-04-23_3_DRREDDY",
      "date": "2026-04-23",
      "captureTime": "18:55",
      "symbol": "DRREDDY",
      "sector": "Pharmaceuticals",
      "signalType": "SELL",
      "entry": 1217,
      "target": 1115.37,
      "stopLoss": 1263.46,
      "rsi": 39.42,
      "techScore": 40,
      "macd": "BULLISH",
      "isSwing": false,
      "status": "PENDING",
      "exitPrice": null,
      "exitTime": null,
      "pnlPct": null,
      "resolvedBy": null,
      "highReached": 1217,
      "lowReached": 1217,
      "lastLTP": 1217
    },
    {
      "signalId": "2026-04-23_4_TRENT",
      "date": "2026-04-23",
      "captureTime": "18:55",
      "symbol": "TRENT",
      "sector": "Speciality Retail",
      "signalType": "STRONG BUY",
      "entry": 4434.5,
      "target": 4915.64,
      "stopLoss": 4196.18,
      "rsi": 92.15,
      "techScore": 75,
      "macd": "BULLISH",
      "isSwing": false,
      "status": "PENDING",
      "exitPrice": null,
      "exitTime": null,
      "pnlPct": null,
      "resolvedBy": null,
      "highReached": 4434.5,
      "lowReached": 4434.5,
      "lastLTP": 4434.5
    },
    {
      "signalId": "2026-04-23_5_VEDL",
      "date": "2026-04-23",
      "captureTime": "18:55",
      "symbol": "VEDL",
      "sector": "Diversified Metals",
      "signalType": "BUY",
      "entry": 757,
      "target": 841.22,
      "stopLoss": 733.94,
      "rsi": 81.31,
      "techScore": 70,
      "macd": "BULLISH",
      "isSwing": false,
      "status": "PENDING",
      "exitPrice": null,
      "exitTime": null,
      "pnlPct": null,
      "resolvedBy": null,
      "highReached": 757,
      "lowReached": 757,
      "lastLTP": 757
    },
    {
      "signalId": "2026-04-23_6_UNIONBANK",
      "date": "2026-04-23",
      "captureTime": "18:55",
      "symbol": "UNIONBANK",
      "sector": "Public Sector Bank",
      "signalType": "BUY",
      "entry": 194.05,
      "target": 212.62,
      "stopLoss": 180.76,
      "rsi": 82.87,
      "techScore": 70,
      "macd": "BULLISH",
      "isSwing": false,
      "status": "PENDING",
      "exitPrice": null,
      "exitTime": null,
      "pnlPct": null,
      "resolvedBy": null,
      "highReached": 194.05,
      "lowReached": 194.05,
      "lastLTP": 194.05
    },
    {
      "signalId": "2026-04-23_7_GVT_D",
      "date": "2026-04-23",
      "captureTime": "18:55",
      "symbol": "GVT&D",
      "sector": "Heavy Electrical Equipment",
      "signalType": "STRONG BUY",
      "entry": 4239.4,
      "target": 4837.15,
      "stopLoss": 3962.58,
      "rsi": 78.72,
      "techScore": 75,
      "macd": "BULLISH",
      "isSwing": false,
      "status": "PENDING",
      "exitPrice": null,
      "exitTime": null,
      "pnlPct": null,
      "resolvedBy": null,
      "highReached": 4239.4,
      "lowReached": 4239.4,
      "lastLTP": 4239.4
    },
    {
      "signalId": "2026-04-23_8_PPLPHARMA",
      "date": "2026-04-23",
      "captureTime": "18:55",
      "symbol": "PPLPHARMA",
      "sector": "Pharmaceuticals",
      "signalType": "BUY",
      "entry": 153.81,
      "target": 165.38,
      "stopLoss": 143.38,
      "rsi": 86.02,
      "techScore": 70,
      "macd": "BULLISH",
      "isSwing": false,
      "status": "PENDING",
      "exitPrice": null,
      "exitTime": null,
      "pnlPct": null,
      "resolvedBy": null,
      "highReached": 153.81,
      "lowReached": 153.81,
      "lastLTP": 153.81
    },
    {
      "signalId": "2026-04-23_9_BAJFINANCE",
      "date": "2026-04-23",
      "captureTime": "18:55",
      "symbol": "BAJFINANCE",
      "sector": "Non Banking Financial Company (NBFC)",
      "signalType": "BUY",
      "entry": 934.75,
      "target": 1030.97,
      "stopLoss": 891.52,
      "rsi": 78.87,
      "techScore": 70,
      "macd": "BULLISH",
      "isSwing": false,
      "status": "PENDING",
      "exitPrice": null,
      "exitTime": null,
      "pnlPct": null,
      "resolvedBy": null,
      "highReached": 934.75,
      "lowReached": 934.75,
      "lastLTP": 934.75
    },
    {
      "signalId": "2026-04-23_10_ADANIGREEN",
      "date": "2026-04-23",
      "captureTime": "18:55",
      "symbol": "ADANIGREEN",
      "sector": "Power Generation",
      "signalType": "STRONG BUY",
      "entry": 1198.95,
      "target": 1305.96,
      "stopLoss": 1075.02,
      "rsi": 99.32,
      "techScore": 75,
      "macd": "BULLISH",
      "isSwing": false,
      "status": "PENDING",
      "exitPrice": null,
      "exitTime": null,
      "pnlPct": null,
      "resolvedBy": null,
      "highReached": 1198.95,
      "lowReached": 1198.95,
      "lastLTP": 1198.95
    },
    {
      "signalId": "2026-04-23_11_DIXON",
      "date": "2026-04-23",
      "captureTime": "18:55",
      "symbol": "DIXON",
      "sector": "Consumer Electronics",
      "signalType": "BUY",
      "entry": 11267,
      "target": 12387.21,
      "stopLoss": 10703.9,
      "rsi": 77.04,
      "techScore": 70,
      "macd": "BULLISH",
      "isSwing": false,
      "status": "PENDING",
      "exitPrice": null,
      "exitTime": null,
      "pnlPct": null,
      "resolvedBy": null,
      "highReached": 11267,
      "lowReached": 11267,
      "lastLTP": 11267
    },
    {
      "signalId": "2026-04-23_12_TVSMOTOR",
      "date": "2026-04-23",
      "captureTime": "18:55",
      "symbol": "TVSMOTOR",
      "sector": "2/3 Wheelers",
      "signalType": "BUY",
      "entry": 3660.7,
      "target": 4063.73,
      "stopLoss": 3554.29,
      "rsi": 66.47,
      "techScore": 70,
      "macd": "BULLISH",
      "isSwing": false,
      "status": "PENDING",
      "exitPrice": null,
      "exitTime": null,
      "pnlPct": null,
      "resolvedBy": null,
      "highReached": 3660.7,
      "lowReached": 3660.7,
      "lastLTP": 3660.7
    },
    {
      "signalId": "2026-04-23_13_HAVELLS",
      "date": "2026-04-23",
      "captureTime": "18:55",
      "symbol": "HAVELLS",
      "sector": "Consumer Electronics",
      "signalType": "BUY",
      "entry": 1348.7,
      "target": 1466.23,
      "stopLoss": 1270.89,
      "rsi": 89.08,
      "techScore": 70,
      "macd": "BULLISH",
      "isSwing": false,
      "status": "PENDING",
      "exitPrice": null,
      "exitTime": null,
      "pnlPct": null,
      "resolvedBy": null,
      "highReached": 1348.7,
      "lowReached": 1348.7,
      "lastLTP": 1348.7
    },
    {
      "signalId": "2026-04-23_14_CLEAN",
      "date": "2026-04-23",
      "captureTime": "18:55",
      "symbol": "CLEAN",
      "sector": "Specialty Chemicals",
      "signalType": "BUY",
      "entry": 765.55,
      "target": 840.89,
      "stopLoss": 711.83,
      "rsi": 75.7,
      "techScore": 70,
      "macd": "BULLISH",
      "isSwing": false,
      "status": "PENDING",
      "exitPrice": null,
      "exitTime": null,
      "pnlPct": null,
      "resolvedBy": null,
      "highReached": 765.55,
      "lowReached": 765.55,
      "lastLTP": 765.55
    },
    {
      "signalId": "2026-04-23_15_ADANIENT",
      "date": "2026-04-23",
      "captureTime": "18:55",
      "symbol": "ADANIENT",
      "sector": "Trading - Minerals",
      "signalType": "STRONG BUY",
      "entry": 2260.8,
      "target": 2480.43,
      "stopLoss": 2103.29,
      "rsi": 93.84,
      "techScore": 75,
      "macd": "BULLISH",
      "isSwing": false,
      "status": "PENDING",
      "exitPrice": null,
      "exitTime": null,
      "pnlPct": null,
      "resolvedBy": null,
      "highReached": 2260.8,
      "lowReached": 2260.8,
      "lastLTP": 2260.8
    },
    {
      "signalId": "2026-04-23_16_POWERINDIA",
      "date": "2026-04-23",
      "captureTime": "18:55",
      "symbol": "POWERINDIA",
      "sector": "Heavy Electrical Equipment",
      "signalType": "STRONG BUY",
      "entry": 30335,
      "target": 32980,
      "stopLoss": 28367.5,
      "rsi": 91.9,
      "techScore": 75,
      "macd": "BULLISH",
      "isSwing": false,
      "status": "PENDING",
      "exitPrice": null,
      "exitTime": null,
      "pnlPct": null,
      "resolvedBy": null,
      "highReached": 30335,
      "lowReached": 30335,
      "lastLTP": 30335
    },
    {
      "signalId": "2026-04-23_17_TECHM",
      "date": "2026-04-23",
      "captureTime": "18:55",
      "symbol": "TECHM",
      "sector": "Computers - Software & Consulting",
      "signalType": "BUY",
      "entry": 1462.6,
      "target": 1594.17,
      "stopLoss": 1398.02,
      "rsi": 64.42,
      "techScore": 62,
      "macd": "BULLISH",
      "isSwing": false,
      "status": "PENDING",
      "exitPrice": null,
      "exitTime": null,
      "pnlPct": null,
      "resolvedBy": null,
      "highReached": 1462.6,
      "lowReached": 1462.6,
      "lastLTP": 1462.6
    },
    {
      "signalId": "2026-04-23_18_ASHOKLEY",
      "date": "2026-04-23",
      "captureTime": "18:55",
      "symbol": "ASHOKLEY",
      "sector": "Commercial Vehicles",
      "signalType": "BUY",
      "entry": 178.97,
      "target": 198.79,
      "stopLoss": 165.36,
      "rsi": 72.08,
      "techScore": 70,
      "macd": "BULLISH",
      "isSwing": false,
      "status": "PENDING",
      "exitPrice": null,
      "exitTime": null,
      "pnlPct": null,
      "resolvedBy": null,
      "highReached": 178.97,
      "lowReached": 178.97,
      "lastLTP": 178.97
    },
    {
      "signalId": "2026-04-23_19_WELCORP",
      "date": "2026-04-23",
      "captureTime": "18:55",
      "symbol": "WELCORP",
      "sector": "Iron & Steel Products",
      "signalType": "STRONG BUY",
      "entry": 1139.2,
      "target": 1239.35,
      "stopLoss": 1048.33,
      "rsi": 99.85,
      "techScore": 75,
      "macd": "BULLISH",
      "isSwing": false,
      "status": "PENDING",
      "exitPrice": null,
      "exitTime": null,
      "pnlPct": null,
      "resolvedBy": null,
      "highReached": 1139.2,
      "lowReached": 1139.2,
      "lastLTP": 1139.2
    },
    {
      "signalId": "2026-04-23_20_ONESOURCE",
      "date": "2026-04-23",
      "captureTime": "18:55",
      "symbol": "ONESOURCE",
      "sector": "Pharmaceuticals",
      "signalType": "STRONG BUY",
      "entry": 1611,
      "target": 1781.88,
      "stopLoss": 1456.26,
      "rsi": 64.28,
      "techScore": 85,
      "macd": "BULLISH",
      "isSwing": false,
      "status": "PENDING",
      "exitPrice": null,
      "exitTime": null,
      "pnlPct": null,
      "resolvedBy": null,
      "highReached": 1611,
      "lowReached": 1611,
      "lastLTP": 1611
    },
    {
      "signalId": "2026-04-23_21_ZEEL",
      "date": "2026-04-23",
      "captureTime": "18:55",
      "symbol": "ZEEL",
      "sector": "TV Broadcasting & Software Production",
      "signalType": "BUY",
      "entry": 87.58,
      "target": 98.67,
      "stopLoss": 80.27,
      "rsi": 74.7,
      "techScore": 70,
      "macd": "BULLISH",
      "isSwing": false,
      "status": "PENDING",
      "exitPrice": null,
      "exitTime": null,
      "pnlPct": null,
      "resolvedBy": null,
      "highReached": 87.58,
      "lowReached": 87.58,
      "lastLTP": 87.58
    },
    {
      "signalId": "2026-04-23_22_COALINDIA",
      "date": "2026-04-23",
      "captureTime": "18:55",
      "symbol": "COALINDIA",
      "sector": "Coal",
      "signalType": "BUY",
      "entry": 444.15,
      "target": 478.45,
      "stopLoss": 426.48,
      "rsi": 45.47,
      "techScore": 60,
      "macd": "BEARISH",
      "isSwing": false,
      "status": "PENDING",
      "exitPrice": null,
      "exitTime": null,
      "pnlPct": null,
      "resolvedBy": null,
      "highReached": 444.15,
      "lowReached": 444.15,
      "lastLTP": 444.15
    },
    {
      "signalId": "2026-04-23_23_GLENMARK",
      "date": "2026-04-23",
      "captureTime": "18:55",
      "symbol": "GLENMARK",
      "sector": "Pharmaceuticals",
      "signalType": "BUY",
      "entry": 2240,
      "target": 2437.52,
      "stopLoss": 2130.89,
      "rsi": 70.5,
      "techScore": 70,
      "macd": "BULLISH",
      "isSwing": false,
      "status": "PENDING",
      "exitPrice": null,
      "exitTime": null,
      "pnlPct": null,
      "resolvedBy": null,
      "highReached": 2240,
      "lowReached": 2240,
      "lastLTP": 2240
    },
    {
      "signalId": "2026-04-23_24_TMCV",
      "date": "2026-04-23",
      "captureTime": "18:55",
      "symbol": "TMCV",
      "sector": "Commercial Vehicles",
      "signalType": "BUY",
      "entry": 447.8,
      "target": 496.47,
      "stopLoss": 414.84,
      "rsi": 71.63,
      "techScore": 70,
      "macd": "BULLISH",
      "isSwing": false,
      "status": "PENDING",
      "exitPrice": null,
      "exitTime": null,
      "pnlPct": null,
      "resolvedBy": null,
      "highReached": 447.8,
      "lowReached": 447.8,
      "lastLTP": 447.8
    },
    {
      "signalId": "2026-04-23_25_IIFL",
      "date": "2026-04-23",
      "captureTime": "18:55",
      "symbol": "IIFL",
      "sector": "Non Banking Financial Company (NBFC)",
      "signalType": "BUY",
      "entry": 467.65,
      "target": 528.25,
      "stopLoss": 454.23,
      "rsi": 65.44,
      "techScore": 62,
      "macd": "BULLISH",
      "isSwing": false,
      "status": "PENDING",
      "exitPrice": null,
      "exitTime": null,
      "pnlPct": null,
      "resolvedBy": null,
      "highReached": 467.65,
      "lowReached": 467.65,
      "lastLTP": 467.65
    },
    {
      "signalId": "2026-04-23_26_ASIANPAINT",
      "date": "2026-04-23",
      "captureTime": "18:55",
      "symbol": "ASIANPAINT",
      "sector": "Paints",
      "signalType": "STRONG BUY",
      "entry": 2562.9,
      "target": 2724.7,
      "stopLoss": 2387.65,
      "rsi": 85.93,
      "techScore": 75,
      "macd": "BULLISH",
      "isSwing": false,
      "status": "PENDING",
      "exitPrice": null,
      "exitTime": null,
      "pnlPct": null,
      "resolvedBy": null,
      "highReached": 2562.9,
      "lowReached": 2562.9,
      "lastLTP": 2562.9
    },
    {
      "signalId": "2026-04-23_27_EICHERMOT",
      "date": "2026-04-23",
      "captureTime": "18:55",
      "symbol": "EICHERMOT",
      "sector": "2/3 Wheelers",
      "signalType": "STRONG BUY",
      "entry": 7230,
      "target": 7875,
      "stopLoss": 6885,
      "rsi": 67.16,
      "techScore": 85,
      "macd": "BULLISH",
      "isSwing": false,
      "status": "PENDING",
      "exitPrice": null,
      "exitTime": null,
      "pnlPct": null,
      "resolvedBy": null,
      "highReached": 7230,
      "lowReached": 7230,
      "lastLTP": 7230
    },
    {
      "signalId": "2026-04-23_28_EMMVEE",
      "date": "2026-04-23",
      "captureTime": "18:55",
      "symbol": "EMMVEE",
      "sector": "Other Electrical Equipment",
      "signalType": "STRONG BUY",
      "entry": 264.68,
      "target": 304.33,
      "stopLoss": 240.84,
      "rsi": 82.35,
      "techScore": 75,
      "macd": "BULLISH",
      "isSwing": false,
      "status": "PENDING",
      "exitPrice": null,
      "exitTime": null,
      "pnlPct": null,
      "resolvedBy": null,
      "highReached": 264.68,
      "lowReached": 264.68,
      "lastLTP": 264.68
    },
    {
      "signalId": "2026-04-23_29_FORCEMOT",
      "date": "2026-04-23",
      "captureTime": "18:55",
      "symbol": "FORCEMOT",
      "sector": "Passenger Cars & Utility Vehicles",
      "signalType": "STRONG BUY",
      "entry": 21770,
      "target": 25038.21,
      "stopLoss": 20330.9,
      "rsi": 65.73,
      "techScore": 78,
      "macd": "BULLISH",
      "isSwing": false,
      "status": "PENDING",
      "exitPrice": null,
      "exitTime": null,
      "pnlPct": null,
      "resolvedBy": null,
      "highReached": 21770,
      "lowReached": 21770,
      "lastLTP": 21770
    },
    {
      "signalId": "2026-04-23_30_CANBK",
      "date": "2026-04-23",
      "captureTime": "18:55",
      "symbol": "CANBK",
      "sector": "Public Sector Bank",
      "signalType": "BUY",
      "entry": 145.23,
      "target": 157.28,
      "stopLoss": 137.17,
      "rsi": 85.15,
      "techScore": 70,
      "macd": "BULLISH",
      "isSwing": false,
      "status": "PENDING",
      "exitPrice": null,
      "exitTime": null,
      "pnlPct": null,
      "resolvedBy": null,
      "highReached": 145.23,
      "lowReached": 145.23,
      "lastLTP": 145.23
    },
    {
      "signalId": "2026-04-23_31_GODREJIND",
      "date": "2026-04-23",
      "captureTime": "18:55",
      "symbol": "GODREJIND",
      "sector": "Diversified",
      "signalType": "BUY",
      "entry": 943.15,
      "target": 1048.33,
      "stopLoss": 867.84,
      "rsi": 91.37,
      "techScore": 70,
      "macd": "BULLISH",
      "isSwing": false,
      "status": "PENDING",
      "exitPrice": null,
      "exitTime": null,
      "pnlPct": null,
      "resolvedBy": null,
      "highReached": 943.15,
      "lowReached": 943.15,
      "lastLTP": 943.15
    },
    {
      "signalId": "2026-04-23_32_MOTHERSON",
      "date": "2026-04-23",
      "captureTime": "18:55",
      "symbol": "MOTHERSON",
      "sector": "Auto Components & Equipments",
      "signalType": "BUY",
      "entry": 131.76,
      "target": 140.23,
      "stopLoss": 116.97,
      "rsi": 81.79,
      "techScore": 70,
      "macd": "BULLISH",
      "isSwing": false,
      "status": "PENDING",
      "exitPrice": null,
      "exitTime": null,
      "pnlPct": null,
      "resolvedBy": null,
      "highReached": 131.76,
      "lowReached": 131.76,
      "lastLTP": 131.76
    },
    {
      "signalId": "2026-04-23_33_INDHOTEL",
      "date": "2026-04-23",
      "captureTime": "18:55",
      "symbol": "INDHOTEL",
      "sector": "Hotels & Resorts",
      "signalType": "BUY",
      "entry": 659.7,
      "target": 723.26,
      "stopLoss": 632.72,
      "rsi": 83.08,
      "techScore": 70,
      "macd": "BULLISH",
      "isSwing": false,
      "status": "PENDING",
      "exitPrice": null,
      "exitTime": null,
      "pnlPct": null,
      "resolvedBy": null,
      "highReached": 659.7,
      "lowReached": 659.7,
      "lastLTP": 659.7
    },
    {
      "signalId": "2026-04-23_34_RECLTD",
      "date": "2026-04-23",
      "captureTime": "18:55",
      "symbol": "RECLTD",
      "sector": "Financial Institution",
      "signalType": "BUY",
      "entry": 383.35,
      "target": 416.66,
      "stopLoss": 361.67,
      "rsi": 96.66,
      "techScore": 70,
      "macd": "BULLISH",
      "isSwing": false,
      "status": "PENDING",
      "exitPrice": null,
      "exitTime": null,
      "pnlPct": null,
      "resolvedBy": null,
      "highReached": 383.35,
      "lowReached": 383.35,
      "lastLTP": 383.35
    },
    {
      "signalId": "2026-04-23_35_GRASIM",
      "date": "2026-04-23",
      "captureTime": "18:55",
      "symbol": "GRASIM",
      "sector": "Cement & Cement Products",
      "signalType": "BUY",
      "entry": 2776.6,
      "target": 2981.73,
      "stopLoss": 2670.74,
      "rsi": 76.23,
      "techScore": 70,
      "macd": "BULLISH",
      "isSwing": false,
      "status": "PENDING",
      "exitPrice": null,
      "exitTime": null,
      "pnlPct": null,
      "resolvedBy": null,
      "highReached": 2776.6,
      "lowReached": 2776.6,
      "lastLTP": 2776.6
    },
    {
      "signalId": "2026-04-23_36_BANKBARODA",
      "date": "2026-04-23",
      "captureTime": "18:55",
      "symbol": "BANKBARODA",
      "sector": "Public Sector Bank",
      "signalType": "BUY",
      "entry": 282.77,
      "target": 307.37,
      "stopLoss": 271.19,
      "rsi": 84.88,
      "techScore": 70,
      "macd": "BULLISH",
      "isSwing": false,
      "status": "PENDING",
      "exitPrice": null,
      "exitTime": null,
      "pnlPct": null,
      "resolvedBy": null,
      "highReached": 282.77,
      "lowReached": 282.77,
      "lastLTP": 282.77
    },
    {
      "signalId": "2026-04-23_37_TORNTPOWER",
      "date": "2026-04-23",
      "captureTime": "18:55",
      "symbol": "TORNTPOWER",
      "sector": "Integrated Power Utilities",
      "signalType": "BUY",
      "entry": 1657.4,
      "target": 1768.75,
      "stopLoss": 1547.13,
      "rsi": 98.01,
      "techScore": 70,
      "macd": "BULLISH",
      "isSwing": false,
      "status": "PENDING",
      "exitPrice": null,
      "exitTime": null,
      "pnlPct": null,
      "resolvedBy": null,
      "highReached": 1657.4,
      "lowReached": 1657.4,
      "lastLTP": 1657.4
    },
    {
      "signalId": "2026-04-23_38_PNB",
      "date": "2026-04-23",
      "captureTime": "18:55",
      "symbol": "PNB",
      "sector": "Public Sector Bank",
      "signalType": "BUY",
      "entry": 114.67,
      "target": 123.92,
      "stopLoss": 108.89,
      "rsi": 78.6,
      "techScore": 63,
      "macd": "BULLISH",
      "isSwing": false,
      "status": "PENDING",
      "exitPrice": null,
      "exitTime": null,
      "pnlPct": null,
      "resolvedBy": null,
      "highReached": 114.67,
      "lowReached": 114.67,
      "lastLTP": 114.67
    },
    {
      "signalId": "2026-04-23_39_DLF",
      "date": "2026-04-23",
      "captureTime": "18:55",
      "symbol": "DLF",
      "sector": "Residential Commercial Projects",
      "signalType": "BUY",
      "entry": 610.65,
      "target": 667.14,
      "stopLoss": 577.23,
      "rsi": 88.2,
      "techScore": 70,
      "macd": "BULLISH",
      "isSwing": false,
      "status": "PENDING",
      "exitPrice": null,
      "exitTime": null,
      "pnlPct": null,
      "resolvedBy": null,
      "highReached": 610.65,
      "lowReached": 610.65,
      "lastLTP": 610.65
    },
    {
      "signalId": "2026-04-23_40_BAJAJFINSV",
      "date": "2026-04-23",
      "captureTime": "18:55",
      "symbol": "BAJAJFINSV",
      "sector": "Holding Company",
      "signalType": "BUY",
      "entry": 1842.9,
      "target": 1995.68,
      "stopLoss": 1772.66,
      "rsi": 81.71,
      "techScore": 63,
      "macd": "BULLISH",
      "isSwing": false,
      "status": "PENDING",
      "exitPrice": null,
      "exitTime": null,
      "pnlPct": null,
      "resolvedBy": null,
      "highReached": 1842.9,
      "lowReached": 1842.9,
      "lastLTP": 1842.9
    },
    {
      "signalId": "2026-04-23_41_ZYDUSLIFE",
      "date": "2026-04-23",
      "captureTime": "18:55",
      "symbol": "ZYDUSLIFE",
      "sector": "Pharmaceuticals",
      "signalType": "BUY",
      "entry": 929.9,
      "target": 990.68,
      "stopLoss": 893.66,
      "rsi": 77.85,
      "techScore": 70,
      "macd": "BULLISH",
      "isSwing": false,
      "status": "PENDING",
      "exitPrice": null,
      "exitTime": null,
      "pnlPct": null,
      "resolvedBy": null,
      "highReached": 929.9,
      "lowReached": 929.9,
      "lastLTP": 929.9
    },
    {
      "signalId": "2026-04-23_42_VOLTAS",
      "date": "2026-04-23",
      "captureTime": "18:55",
      "symbol": "VOLTAS",
      "sector": "Household Appliances",
      "signalType": "STRONG BUY",
      "entry": 1481.6,
      "target": 1624.81,
      "stopLoss": 1377.45,
      "rsi": 79.71,
      "techScore": 75,
      "macd": "BULLISH",
      "isSwing": false,
      "status": "PENDING",
      "exitPrice": null,
      "exitTime": null,
      "pnlPct": null,
      "resolvedBy": null,
      "highReached": 1481.6,
      "lowReached": 1481.6,
      "lastLTP": 1481.6
    },
    {
      "signalId": "2026-04-23_43_BLUESTARCO",
      "date": "2026-04-23",
      "captureTime": "18:55",
      "symbol": "BLUESTARCO",
      "sector": "Household Appliances",
      "signalType": "STRONG BUY",
      "entry": 1888.6,
      "target": 2113.91,
      "stopLoss": 1763.05,
      "rsi": 76.17,
      "techScore": 75,
      "macd": "BULLISH",
      "isSwing": false,
      "status": "PENDING",
      "exitPrice": null,
      "exitTime": null,
      "pnlPct": null,
      "resolvedBy": null,
      "highReached": 1888.6,
      "lowReached": 1888.6,
      "lastLTP": 1888.6
    },
    {
      "signalId": "2026-04-23_44_GODREJPROP",
      "date": "2026-04-23",
      "captureTime": "18:55",
      "symbol": "GODREJPROP",
      "sector": "Residential Commercial Projects",
      "signalType": "BUY",
      "entry": 1832.2,
      "target": 2008.25,
      "stopLoss": 1711.48,
      "rsi": 95.83,
      "techScore": 70,
      "macd": "BULLISH",
      "isSwing": false,
      "status": "PENDING",
      "exitPrice": null,
      "exitTime": null,
      "pnlPct": null,
      "resolvedBy": null,
      "highReached": 1832.2,
      "lowReached": 1832.2,
      "lastLTP": 1832.2
    },
    {
      "signalId": "2026-04-23_45_CROMPTON",
      "date": "2026-04-23",
      "captureTime": "18:55",
      "symbol": "CROMPTON",
      "sector": "Household Appliances",
      "signalType": "BUY",
      "entry": 261.37,
      "target": 285.15,
      "stopLoss": 244.43,
      "rsi": 76.84,
      "techScore": 70,
      "macd": "BULLISH",
      "isSwing": false,
      "status": "PENDING",
      "exitPrice": null,
      "exitTime": null,
      "pnlPct": null,
      "resolvedBy": null,
      "highReached": 261.37,
      "lowReached": 261.37,
      "lastLTP": 261.37
    },
    {
      "signalId": "2026-04-23_46_LGEINDIA",
      "date": "2026-04-23",
      "captureTime": "18:55",
      "symbol": "LGEINDIA",
      "sector": "Household Appliances",
      "signalType": "STRONG BUY",
      "entry": 1608.2,
      "target": 1811.4,
      "stopLoss": 1510.8,
      "rsi": 69.98,
      "techScore": 90,
      "macd": "BULLISH",
      "isSwing": false,
      "status": "PENDING",
      "exitPrice": null,
      "exitTime": null,
      "pnlPct": null,
      "resolvedBy": null,
      "highReached": 1608.2,
      "lowReached": 1608.2,
      "lastLTP": 1608.2
    },
    {
      "signalId": "2026-04-23_47_KIMS",
      "date": "2026-04-23",
      "captureTime": "18:55",
      "symbol": "KIMS",
      "sector": "Hospital",
      "signalType": "BUY",
      "entry": 681.7,
      "target": 735.89,
      "stopLoss": 652.05,
      "rsi": 84.92,
      "techScore": 70,
      "macd": "BULLISH",
      "isSwing": false,
      "status": "PENDING",
      "exitPrice": null,
      "exitTime": null,
      "pnlPct": null,
      "resolvedBy": null,
      "highReached": 681.7,
      "lowReached": 681.7,
      "lastLTP": 681.7
    },
    {
      "signalId": "2026-04-23_48_APLAPOLLO",
      "date": "2026-04-23",
      "captureTime": "18:55",
      "symbol": "APLAPOLLO",
      "sector": "Iron & Steel Products",
      "signalType": "STRONG BUY",
      "entry": 2121.9,
      "target": 2341.22,
      "stopLoss": 2002.19,
      "rsi": 66.27,
      "techScore": 85,
      "macd": "BULLISH",
      "isSwing": false,
      "status": "PENDING",
      "exitPrice": null,
      "exitTime": null,
      "pnlPct": null,
      "resolvedBy": null,
      "highReached": 2121.9,
      "lowReached": 2121.9,
      "lastLTP": 2121.9
    },
    {
      "signalId": "2026-04-23_49_JUBLINGREA",
      "date": "2026-04-23",
      "captureTime": "18:55",
      "symbol": "JUBLINGREA",
      "sector": "Specialty Chemicals",
      "signalType": "BUY",
      "entry": 698.95,
      "target": 752.5,
      "stopLoss": 617.28,
      "rsi": 90.02,
      "techScore": 70,
      "macd": "BULLISH",
      "isSwing": false,
      "status": "PENDING",
      "exitPrice": null,
      "exitTime": null,
      "pnlPct": null,
      "resolvedBy": null,
      "highReached": 698.95,
      "lowReached": 698.95,
      "lastLTP": 698.95
    },
    {
      "signalId": "2026-04-23_50_SAILIFE",
      "date": "2026-04-23",
      "captureTime": "18:55",
      "symbol": "SAILIFE",
      "sector": "Pharmaceuticals",
      "signalType": "BUY",
      "entry": 1006,
      "target": 1065.62,
      "stopLoss": 905.69,
      "rsi": 59.49,
      "techScore": 65,
      "macd": "BEARISH",
      "isSwing": false,
      "status": "PENDING",
      "exitPrice": null,
      "exitTime": null,
      "pnlPct": null,
      "resolvedBy": null,
      "highReached": 1006,
      "lowReached": 1006,
      "lastLTP": 1006
    },
    {
      "signalId": "2026-04-23_51_ALKEM",
      "date": "2026-04-23",
      "captureTime": "18:55",
      "symbol": "ALKEM",
      "sector": "Pharmaceuticals",
      "signalType": "STRONG BUY",
      "entry": 5627,
      "target": 6158.46,
      "stopLoss": 5448.27,
      "rsi": 68.04,
      "techScore": 85,
      "macd": "BULLISH",
      "isSwing": false,
      "status": "PENDING",
      "exitPrice": null,
      "exitTime": null,
      "pnlPct": null,
      "resolvedBy": null,
      "highReached": 5627,
      "lowReached": 5627,
      "lastLTP": 5627
    },
    {
      "signalId": "2026-04-23_52_MPHASIS",
      "date": "2026-04-23",
      "captureTime": "18:55",
      "symbol": "MPHASIS",
      "sector": "Computers - Software & Consulting",
      "signalType": "SELL",
      "entry": 2331,
      "target": 2119.06,
      "stopLoss": 2525.32,
      "rsi": 70.36,
      "techScore": 40,
      "macd": "BULLISH",
      "isSwing": false,
      "status": "PENDING",
      "exitPrice": null,
      "exitTime": null,
      "pnlPct": null,
      "resolvedBy": null,
      "highReached": 2331,
      "lowReached": 2331,
      "lastLTP": 2331
    },
    {
      "signalId": "2026-04-23_53_CPPLUS",
      "date": "2026-04-23",
      "captureTime": "18:55",
      "symbol": "CPPLUS",
      "sector": "Industrial Products",
      "signalType": "STRONG BUY",
      "entry": 2183.9,
      "target": 2595.96,
      "stopLoss": 2090.97,
      "rsi": 82.12,
      "techScore": 75,
      "macd": "BULLISH",
      "isSwing": false,
      "status": "PENDING",
      "exitPrice": null,
      "exitTime": null,
      "pnlPct": null,
      "resolvedBy": null,
      "highReached": 2183.9,
      "lowReached": 2183.9,
      "lastLTP": 2183.9
    },
    {
      "signalId": "2026-04-23_54_NHPC",
      "date": "2026-04-23",
      "captureTime": "18:55",
      "symbol": "NHPC",
      "sector": "Power Generation",
      "signalType": "BUY",
      "entry": 82.63,
      "target": 89.7,
      "stopLoss": 79.35,
      "rsi": 87.41,
      "techScore": 70,
      "macd": "BULLISH",
      "isSwing": false,
      "status": "PENDING",
      "exitPrice": null,
      "exitTime": null,
      "pnlPct": null,
      "resolvedBy": null,
      "highReached": 82.63,
      "lowReached": 82.63,
      "lastLTP": 82.63
    },
    {
      "signalId": "2026-04-23_55_LTTS",
      "date": "2026-04-23",
      "captureTime": "18:55",
      "symbol": "LTTS",
      "sector": "IT Enabled Services",
      "signalType": "STRONG BUY",
      "entry": 3550.2,
      "target": 4035.89,
      "stopLoss": 3444.91,
      "rsi": 74.03,
      "techScore": 75,
      "macd": "BULLISH",
      "isSwing": false,
      "status": "PENDING",
      "exitPrice": null,
      "exitTime": null,
      "pnlPct": null,
      "resolvedBy": null,
      "highReached": 3550.2,
      "lowReached": 3550.2,
      "lastLTP": 3550.2
    },
    {
      "signalId": "2026-04-23_56_JMFINANCIL",
      "date": "2026-04-23",
      "captureTime": "18:55",
      "symbol": "JMFINANCIL",
      "sector": "Holding Company",
      "signalType": "BUY",
      "entry": 133.83,
      "target": 148.67,
      "stopLoss": 124.87,
      "rsi": 78.26,
      "techScore": 70,
      "macd": "BULLISH",
      "isSwing": false,
      "status": "PENDING",
      "exitPrice": null,
      "exitTime": null,
      "pnlPct": null,
      "resolvedBy": null,
      "highReached": 133.83,
      "lowReached": 133.83,
      "lastLTP": 133.83
    },
    {
      "signalId": "2026-04-23_57_WHIRLPOOL",
      "date": "2026-04-23",
      "captureTime": "18:55",
      "symbol": "WHIRLPOOL",
      "sector": "Household Appliances",
      "signalType": "BUY",
      "entry": 932.2,
      "target": 1020.42,
      "stopLoss": 866.79,
      "rsi": 79.15,
      "techScore": 70,
      "macd": "BULLISH",
      "isSwing": false,
      "status": "PENDING",
      "exitPrice": null,
      "exitTime": null,
      "pnlPct": null,
      "resolvedBy": null,
      "highReached": 932.2,
      "lowReached": 932.2,
      "lastLTP": 932.2
    },
    {
      "signalId": "2026-04-23_58_GALLANTT",
      "date": "2026-04-23",
      "captureTime": "18:55",
      "symbol": "GALLANTT",
      "sector": "Iron & Steel Products",
      "signalType": "STRONG BUY",
      "entry": 870.55,
      "target": 1056.08,
      "stopLoss": 773.66,
      "rsi": 80.87,
      "techScore": 75,
      "macd": "BULLISH",
      "isSwing": false,
      "status": "PENDING",
      "exitPrice": null,
      "exitTime": null,
      "pnlPct": null,
      "resolvedBy": null,
      "highReached": 870.55,
      "lowReached": 870.55,
      "lastLTP": 870.55
    },
    {
      "signalId": "2026-04-23_59_J_KBANK",
      "date": "2026-04-23",
      "captureTime": "18:55",
      "symbol": "J&KBANK",
      "sector": "Private Sector Bank",
      "signalType": "BUY",
      "entry": 132.82,
      "target": 148.38,
      "stopLoss": 126.06,
      "rsi": 87.83,
      "techScore": 70,
      "macd": "BULLISH",
      "isSwing": false,
      "status": "PENDING",
      "exitPrice": null,
      "exitTime": null,
      "pnlPct": null,
      "resolvedBy": null,
      "highReached": 132.82,
      "lowReached": 132.82,
      "lastLTP": 132.82
    },
    {
      "signalId": "2026-04-23_60_FIVESTAR",
      "date": "2026-04-23",
      "captureTime": "18:55",
      "symbol": "FIVESTAR",
      "sector": "Non Banking Financial Company (NBFC)",
      "signalType": "STRONG BUY",
      "entry": 501,
      "target": 570.85,
      "stopLoss": 466.23,
      "rsi": 90.51,
      "techScore": 75,
      "macd": "BULLISH",
      "isSwing": false,
      "status": "PENDING",
      "exitPrice": null,
      "exitTime": null,
      "pnlPct": null,
      "resolvedBy": null,
      "highReached": 501,
      "lowReached": 501,
      "lastLTP": 501
    },
    {
      "signalId": "2026-04-23_61_CONCOR",
      "date": "2026-04-23",
      "captureTime": "18:55",
      "symbol": "CONCOR",
      "sector": "Logistics Solution Provider",
      "signalType": "BUY",
      "entry": 515.7,
      "target": 548.55,
      "stopLoss": 479.48,
      "rsi": 91.32,
      "techScore": 70,
      "macd": "BULLISH",
      "isSwing": false,
      "status": "PENDING",
      "exitPrice": null,
      "exitTime": null,
      "pnlPct": null,
      "resolvedBy": null,
      "highReached": 515.7,
      "lowReached": 515.7,
      "lastLTP": 515.7
    },
    {
      "signalId": "2026-04-23_62_PHOENIXLTD",
      "date": "2026-04-23",
      "captureTime": "18:55",
      "symbol": "PHOENIXLTD",
      "sector": "Residential Commercial Projects",
      "signalType": "STRONG BUY",
      "entry": 1809.4,
      "target": 1986.13,
      "stopLoss": 1717.44,
      "rsi": 89.33,
      "techScore": 75,
      "macd": "BULLISH",
      "isSwing": false,
      "status": "PENDING",
      "exitPrice": null,
      "exitTime": null,
      "pnlPct": null,
      "resolvedBy": null,
      "highReached": 1809.4,
      "lowReached": 1809.4,
      "lastLTP": 1809.4
    },
    {
      "signalId": "2026-04-23_63_IPCALAB",
      "date": "2026-04-23",
      "captureTime": "18:55",
      "symbol": "IPCALAB",
      "sector": "Pharmaceuticals",
      "signalType": "BUY",
      "entry": 1494.8,
      "target": 1612.91,
      "stopLoss": 1408.3,
      "rsi": 27.93,
      "techScore": 70,
      "macd": "BEARISH",
      "isSwing": false,
      "status": "PENDING",
      "exitPrice": null,
      "exitTime": null,
      "pnlPct": null,
      "resolvedBy": null,
      "highReached": 1494.8,
      "lowReached": 1494.8,
      "lastLTP": 1494.8
    },
    {
      "signalId": "2026-04-23_64_LALPATHLAB",
      "date": "2026-04-23",
      "captureTime": "18:55",
      "symbol": "LALPATHLAB",
      "sector": "Healthcare Service Provider",
      "signalType": "BUY",
      "entry": 1459.1,
      "target": 1577.42,
      "stopLoss": 1374.29,
      "rsi": 77.43,
      "techScore": 70,
      "macd": "BULLISH",
      "isSwing": false,
      "status": "PENDING",
      "exitPrice": null,
      "exitTime": null,
      "pnlPct": null,
      "resolvedBy": null,
      "highReached": 1459.1,
      "lowReached": 1459.1,
      "lastLTP": 1459.1
    },
    {
      "signalId": "2026-04-23_65_EMAMILTD",
      "date": "2026-04-23",
      "captureTime": "18:55",
      "symbol": "EMAMILTD",
      "sector": "Personal Care",
      "signalType": "BUY",
      "entry": 473.2,
      "target": 501.86,
      "stopLoss": 434.5,
      "rsi": 92.45,
      "techScore": 70,
      "macd": "BULLISH",
      "isSwing": false,
      "status": "PENDING",
      "exitPrice": null,
      "exitTime": null,
      "pnlPct": null,
      "resolvedBy": null,
      "highReached": 473.2,
      "lowReached": 473.2,
      "lastLTP": 473.2
    },
    {
      "signalId": "2026-04-23_66_TENNIND",
      "date": "2026-04-23",
      "captureTime": "18:55",
      "symbol": "TENNIND",
      "sector": "Auto Components & Equipments",
      "signalType": "BUY",
      "entry": 591.5,
      "target": 665.34,
      "stopLoss": 562.83,
      "rsi": 81.65,
      "techScore": 70,
      "macd": "BULLISH",
      "isSwing": false,
      "status": "PENDING",
      "exitPrice": null,
      "exitTime": null,
      "pnlPct": null,
      "resolvedBy": null,
      "highReached": 591.5,
      "lowReached": 591.5,
      "lastLTP": 591.5
    },
    {
      "signalId": "2026-04-23_67_BALKRISIND",
      "date": "2026-04-23",
      "captureTime": "18:55",
      "symbol": "BALKRISIND",
      "sector": "Tyres & Rubber Products",
      "signalType": "BUY",
      "entry": 2309.7,
      "target": 2542.72,
      "stopLoss": 2184.79,
      "rsi": 70.89,
      "techScore": 63,
      "macd": "BULLISH",
      "isSwing": false,
      "status": "PENDING",
      "exitPrice": null,
      "exitTime": null,
      "pnlPct": null,
      "resolvedBy": null,
      "highReached": 2309.7,
      "lowReached": 2309.7,
      "lastLTP": 2309.7
    },
    {
      "signalId": "2026-04-23_68_ABFRL",
      "date": "2026-04-23",
      "captureTime": "18:55",
      "symbol": "ABFRL",
      "sector": "Speciality Retail",
      "signalType": "BUY",
      "entry": 64.99,
      "target": 72.9,
      "stopLoss": 60.53,
      "rsi": 82.16,
      "techScore": 70,
      "macd": "BULLISH",
      "isSwing": false,
      "status": "PENDING",
      "exitPrice": null,
      "exitTime": null,
      "pnlPct": null,
      "resolvedBy": null,
      "highReached": 64.99,
      "lowReached": 64.99,
      "lastLTP": 64.99
    },
    {
      "signalId": "2026-04-23_69_SUNTV",
      "date": "2026-04-23",
      "captureTime": "18:55",
      "symbol": "SUNTV",
      "sector": "TV Broadcasting & Software Production",
      "signalType": "BUY",
      "entry": 652.45,
      "target": 715.57,
      "stopLoss": 614.81,
      "rsi": 83.79,
      "techScore": 70,
      "macd": "BULLISH",
      "isSwing": false,
      "status": "PENDING",
      "exitPrice": null,
      "exitTime": null,
      "pnlPct": null,
      "resolvedBy": null,
      "highReached": 652.45,
      "lowReached": 652.45,
      "lastLTP": 652.45
    },
    {
      "signalId": "2026-04-23_70_BLUEDART",
      "date": "2026-04-23",
      "captureTime": "18:55",
      "symbol": "BLUEDART",
      "sector": "Logistics Solution Provider",
      "signalType": "BUY",
      "entry": 5478.3,
      "target": 5988.14,
      "stopLoss": 5218.28,
      "rsi": 85.52,
      "techScore": 70,
      "macd": "BULLISH",
      "isSwing": false,
      "status": "PENDING",
      "exitPrice": null,
      "exitTime": null,
      "pnlPct": null,
      "resolvedBy": null,
      "highReached": 5478.3,
      "lowReached": 5478.3,
      "lastLTP": 5478.3
    },
    {
      "signalId": "2026-04-23_71_BERGEPAINT",
      "date": "2026-04-23",
      "captureTime": "18:55",
      "symbol": "BERGEPAINT",
      "sector": "Paints",
      "signalType": "BUY",
      "entry": 478.25,
      "target": 527.56,
      "stopLoss": 453.22,
      "rsi": 85.79,
      "techScore": 70,
      "macd": "BULLISH",
      "isSwing": false,
      "status": "PENDING",
      "exitPrice": null,
      "exitTime": null,
      "pnlPct": null,
      "resolvedBy": null,
      "highReached": 478.25,
      "lowReached": 478.25,
      "lastLTP": 478.25
    }
  ],
  "sessions": {
    "2026-04-23_18:55": {
      "date": "2026-04-23",
      "captureTime": "18:55",
      "totalSignals": 72,
      "resolved": 0,
      "wins": 0,
      "losses": 0
    }
  }
}